{"goal_meta_link":"http://unstats.un.org/sdgs/files/metadata-compilation/Metadata-Goal-16.pdf","goal_meta_link_text":"custom.meta_link_text","indicator_name":"\u8fc7\u53bb12\u4e2a\u6708\u5185\u5411\u4e3b\u7ba1\u5f53\u5c40\u6216\u5176\u4ed6\u5b98\u65b9\u8ba4\u53ef\u7684\u51b2\u7a81\u89e3\u51b3\u673a\u5236\u62a5\u544a\u5176\u53d7\u5bb3\u7ecf\u5386\u7684\u66b4\u529b\u884c\u4e3a\u53d7\u5bb3\u8005\u6240\u5360\u6bd4\u4f8b","data_non_statistical":false,"graph_type":"bar","graph_title":"\u8fc7\u53bb12\u4e2a\u6708\u5185\u5411\u4e3b\u7ba1\u5f53\u5c40\u6216\u5176\u4ed6\u5b98\u65b9\u8ba4\u53ef\u7684\u51b2\u7a81\u89e3\u51b3\u673a\u5236\u62a5\u544a\u5176\u53d7\u5bb3\u7ecf\u5386\u7684\u66b4\u529b\u884c\u4e3a\u53d7\u5bb3\u8005\u6240\u5360\u6bd4\u4f8b","national_geographical_coverage":"\u041a\u044b\u0440\u0433\u044b\u0437\u0441\u043a\u0430\u044f \u0420\u0435\u0441\u043f\u0443\u0431\u043b\u0438\u043a\u0430","measurement_units":null,"data_footnote":"This data is for women aged 15 to 49.","page_content":"","indicator":"16.3.1","target_id":"16.3","sdg_goal":"16","reporting_status":"complete","indicator_sort_order":"16-03-01"}